LICENSE
MANIFEST.in
README.md
requirements.txt
setup.py
bin/pyg2p
configuration/ftp.json
configuration/geopotentials.json
configuration/intertables.json
configuration/parameters.json
configuration/global/ftp.json
configuration/global/geopotentials.json
configuration/global/global_conf.json
configuration/global/intertables.json
configuration/global/parameters.json
configuration/global/test.json
src/pyg2p.py
src/pyg2p/VERSION
src/pyg2p/__init__.py
src/pyg2p/exceptions.py
src/pyg2p.egg-info/PKG-INFO
src/pyg2p.egg-info/SOURCES.txt
src/pyg2p.egg-info/dependency_links.txt
src/pyg2p.egg-info/not-zip-safe
src/pyg2p.egg-info/requires.txt
src/pyg2p.egg-info/top_level.txt
src/pyg2p/main/__init__.py
src/pyg2p/main/api.py
src/pyg2p/main/config.py
src/pyg2p/main/context.py
src/pyg2p/main/controller.py
src/pyg2p/main/interpolation/__init__.py
src/pyg2p/main/interpolation/grib_interpolation_lib.py
src/pyg2p/main/interpolation/latlong.py
src/pyg2p/main/interpolation/scipy_interpolation_lib.py
src/pyg2p/main/manipulation/__init__.py
src/pyg2p/main/manipulation/aggregator.py
src/pyg2p/main/manipulation/conversion.py
src/pyg2p/main/manipulation/correction.py
src/pyg2p/main/readers/__init__.py
src/pyg2p/main/readers/grib.py
src/pyg2p/main/readers/netcdf.py
src/pyg2p/main/readers/pcr.py
src/pyg2p/main/writers/__init__.py
src/pyg2p/main/writers/netcdf.py
src/pyg2p/main/writers/pcr.py
src/pyg2p/util/__init__.py
src/pyg2p/util/files.py
src/pyg2p/util/generics.py
src/pyg2p/util/numeric.py
src/pyg2p/util/strings.py
src/pyg2p/util/profiling/__init__.py
src/pyg2p/util/profiling/profilehooks.py
templates/AFFS_cp.json
templates/AFFS_lsp.json
templates/AFFS_rg.json
templates/AFFS_rn.json
templates/AFFS_ta.json
templates/AFFS_td.json
templates/AFFS_wu.json
templates/AFFS_wv.json
templates/EUE_15d.json
templates/EUE_15d_glob.json
templates/EUE_RainAnim.json
templates/EUE_RainAnim_CV.json
templates/EUE_RainAnim_CV_g.json
templates/EUE_RainAnim_CV_scipy.json
templates/EUE_RainAnim_CV_scipy_inv.json
templates/EUE_RainAnim_CV_scipy_nn.json
templates/EUE_RainAnim_agg.json
templates/EUE_RainAnim_december.json
templates/EUE_RainAnim_g.json
templates/EUE_RainAnim_scipy.json
