Metadata-Version: 2.1
Name: pyg2p
Version: 3.2.8
Summary: Convert GRIB files to netCDF or PCRaster
Author: Domenico Nappo
Author-email: domenico.nappo@gmail.com
License: EUPL 1.2
Keywords: NetCDF GRIB PCRaster Lisflood EFAS GLOFAS
Classifier: Development Status :: 4 - Beta
Classifier: Intended Audience :: Developers
Classifier: Intended Audience :: Education
Classifier: Intended Audience :: Financial and Insurance Industry
Classifier: Intended Audience :: Other Audience
Classifier: Intended Audience :: Science/Research
Classifier: License :: OSI Approved :: European Union Public Licence 1.2 (EUPL 1.2)
Classifier: Operating System :: Unix
Classifier: Operating System :: POSIX
Classifier: Operating System :: Microsoft :: Windows
Classifier: Operating System :: MacOS :: MacOS X
Classifier: Programming Language :: Python
Classifier: Programming Language :: Python :: 3
Classifier: Topic :: Scientific/Engineering :: Physics
License-File: LICENSE
Requires-Dist: netCDF4<=1.6.4,>=1.5.3
Requires-Dist: ujson>=5.4.0
Requires-Dist: numpy>=1.18.2
Requires-Dist: numba>=0.54.0
Requires-Dist: scipy>=1.6.0
Requires-Dist: numexpr>=2.7.1
Requires-Dist: importlib-metadata<5.0.0
Requires-Dist: dask[bag]
Requires-Dist: dask[array]
Requires-Dist: toolz
Requires-Dist: eccodes
Requires-Dist: lisflood-utilities
